{"py/object": "rasa.core.featurizers.tracker_featurizers.MaxHistoryTrackerFeaturizer", "state_featurizer": {"py/object": "rasa.core.featurizers.single_state_featurizer.SingleStateFeaturizer", "_default_feature_states": {"intent": {"Bank_account_type_an": 0, "Bank_mission_an": 1, "Bank_services_an": 2, "back": 3, "bank_Vision": 4, "bank_Vision_an": 5, "bank_Vision_fr": 6, "bank_account_type": 7, "bank_account_type_fr": 8, "bank_credit_type": 9, "bank_credit_type_an": 10, "bank_credit_type_fr": 11, "bank_mission": 12, "bank_mission_fr": 13, "bank_services": 14, "bank_services_fr": 15, "bank_values_an": 16, "bank_values_fr": 17, "bot_challenge": 18, "bot_challenge_an": 19, "bot_challenge_fr": 20, "goodbye": 21, "goodbye_an": 22, "goodbye_fr": 23, "greet": 24, "greet_an": 25, "greet_fr": 26, "help_confirmation": 27, "help_confirmation_an": 28, "help_confirmation_fr": 29, "help_unconfirmation": 30, "help_unconfirmation_an": 31, "help_unconfirmation_fr": 32, "lost_card": 33, "lost_card_an": 34, "lost_card_fr": 35, "nlu_fallback": 36, "out_of_scope": 37, "restart": 38, "session_start": 39}, "action_name": {"action_listen": 0, "action_restart": 1, "action_session_start": 2, "action_default_fallback": 3, "action_deactivate_loop": 4, "action_revert_fallback_events": 5, "action_default_ask_affirmation": 6, "action_default_ask_rephrase": 7, "action_two_stage_fallback": 8, "action_unlikely_intent": 9, "action_back": 10, "...": 11, "action_extract_slots": 12, "utter_Services_an": 13, "utter_account_type_an": 14, "utter_bank_Vision": 15, "utter_bank_Vision_fr": 16, "utter_bank_account_type": 17, "utter_bank_account_type_fr": 18, "utter_bank_credit_type": 19, "utter_bank_credit_type_fr": 20, "utter_bank_mission": 21, "utter_bank_mission_fr": 22, "utter_bank_services": 23, "utter_bank_services_fr": 24, "utter_bank_values_fr": 25, "utter_bot_an": 26, "utter_bot_challenge": 27, "utter_bot_challenge_fr": 28, "utter_credit_an": 29, "utter_did_that_help": 30, "utter_did_that_help_an": 31, "utter_did_that_help_fr": 32, "utter_goodbye": 33, "utter_goodbye_an": 34, "utter_goodbye_fr": 35, "utter_greet": 36, "utter_greet_an": 37, "utter_greet_fr": 38, "utter_happy": 39, "utter_happy_an": 40, "utter_happy_fr": 41, "utter_lost_card": 42, "utter_lost_card_an": 43, "utter_lost_card_fr": 44, "utter_mission_an": 45, "utter_unhappy": 46, "utter_unhappy_an": 47, "utter_unhappy_fr": 48, "utter_values_an": 49, "utter_vision_an": 50}, "entities": {}, "slots": {}, "active_loop": {}}, "action_texts": [], "entity_tag_specs": null}, "max_history": 5, "remove_duplicates": true}